Data_Quality_Checks_The_Shard/core/__init__.py
Data_Quality_Checks_The_Shard/core/checks.py
Data_Quality_Checks_The_Shard/core/core.py
Data_Quality_Checks_The_Shard/core/schemas.py
Data_Quality_Checks_The_Shard/core/utils.py
Data_Quality_Checks_The_Shard/tests/__init__.py
Data_Quality_Checks_The_Shard/tests/test_checks.py
Data_Quality_Checks_The_Shard/tests/test_schemas.py
data_quality_checks_the_shard-0.0.3.dist-info/LICENSE
data_quality_checks_the_shard-0.0.3.dist-info/METADATA
data_quality_checks_the_shard-0.0.3.dist-info/WHEEL
data_quality_checks_the_shard-0.0.3.dist-info/top_level.txt
data_quality_checks_the_shard-0.0.3.dist-info/RECORD
