Metadata-Version: 2.2
Name: data_quality_checks_the_shard
Version: 0.0.3
Summary: Automate data quality checks before and after ETL into a database.
Author-email: JingYuan Gong <mr.jgong@gmail.com>
License: MIT
Project-URL: Homepage, https://github.com/The-shard-data-science/data-quality-checks-the-shard
Project-URL: Issues, https://github.com/The-shard-data-science/data-quality-checks-the-shard/issues
Classifier: Development Status :: 3 - Alpha
Classifier: Intended Audience :: Developers
Classifier: License :: OSI Approved :: MIT License
Classifier: Programming Language :: Python :: 3
Classifier: Programming Language :: Python :: 3.8
Classifier: Programming Language :: Python :: 3.9
Classifier: Programming Language :: Python :: 3.10
Classifier: Programming Language :: Python :: 3.11
Classifier: Operating System :: OS Independent
Requires-Python: >=3.8
License-File: LICENSE
Requires-Dist: pandas
Requires-Dist: pandera
Requires-Dist: datetime
